morphine/__init__.py
morphine/_astropy_init.py
morphine/accel_math.py
morphine/conftest.py
morphine/dms.py
morphine/fresnel.py
morphine/fwcentroid.py
morphine/geometry.py
morphine/instrument.py
morphine/matrixDFT.py
morphine/misc.py
morphine/morphine_core.py
morphine/optics.py
morphine/physical_wavefront.py
morphine/special_prop.py
morphine/utils.py
morphine/version.py
morphine/wfe.py
morphine/zernike.py
morphine/tests/__init__.py
morphine/tests/coveragerc
morphine/tests/setup_package.py
morphine/tests/test_grad.py
morphine_optics-0.9.3.dist-info/LICENSE.md
morphine_optics-0.9.3.dist-info/LICENSE.txt
morphine_optics-0.9.3.dist-info/METADATA
morphine_optics-0.9.3.dist-info/WHEEL
morphine_optics-0.9.3.dist-info/top_level.txt
morphine_optics-0.9.3.dist-info/RECORD
