Metadata-Version: 2.1
Name: morphine-optics
Version: 0.9.3
Summary: Physical optics propagation (wavefront diffraction) for optical simulations, particularly of telescopes, with analytic derivatives.
Home-page: https://morphine-optics.readthedocs.io/
Author: Marshall Perrin & Benjamin Pope
Author-email: benjamin.pope@nyu.edu
License: BSD
Platform: UNKNOWN
Provides: morphine
Requires-Python: >=3.5
Requires-Dist: numpy (>=1.13.0)
Requires-Dist: scipy (>=1.0.0)
Requires-Dist: matplotlib (>=2.0.0)
Requires-Dist: astropy (>=3.0.0)
Requires-Dist: jaxlib (==0.1.55)
Requires-Dist: jax (==0.1.77)
